pyoncoprint/__init__.py
pyoncoprint-0.2.6.dist-info/licenses/LICENSE
pyoncoprint-0.2.6.dist-info/METADATA
pyoncoprint-0.2.6.dist-info/WHEEL
pyoncoprint-0.2.6.dist-info/top_level.txt
pyoncoprint-0.2.6.dist-info/RECORD
