Metadata-Version: 2.4
Name: pyoncoprint
Version: 0.2.6
Summary: PyOncoPrint
Author-email: Jeongbin Park <jeongbin.park@pusan.ac.kr>
License: BSD-2-Clause
Project-URL: Homepage, https://pnucolab.com
Project-URL: Repository, https://github.com/pnucolab/pyoncoprint
Classifier: Programming Language :: Python :: 3
Classifier: License :: OSI Approved :: BSD License
Classifier: Operating System :: POSIX
Requires-Python: >=3.7
License-File: LICENSE
Requires-Dist: numpy
Requires-Dist: pandas
Requires-Dist: matplotlib
Dynamic: license-file
